spherical_hashing/__init__.py
spherical_hashing/spherical_hashing.py
tf_spherical_hashing-0.0.1.dist-info/LICENSE
tf_spherical_hashing-0.0.1.dist-info/METADATA
tf_spherical_hashing-0.0.1.dist-info/WHEEL
tf_spherical_hashing-0.0.1.dist-info/top_level.txt
tf_spherical_hashing-0.0.1.dist-info/RECORD
