Metadata-Version: 2.1
Name: tf-spherical-hashing
Version: 0.0.1
Summary: Tensorflow implementation of Spherical Hashing.
Home-page: https://github.com/johnPertoft/spherical-hashing
Author: John Pertoft
Author-email: john.pertoft@gmail.com
License: UNKNOWN
Platform: UNKNOWN
Classifier: Programming Language :: Python :: 3
Classifier: License :: OSI Approved :: MIT License
Requires-Dist: tensorflow (>=2.0)
